README.md
remoteunrar.py
setup.py
bin/remoteunrar
remoteunrar.egg-info/PKG-INFO
remoteunrar.egg-info/SOURCES.txt
remoteunrar.egg-info/dependency_links.txt
remoteunrar.egg-info/requires.txt
remoteunrar.egg-info/top_level.txt