Metadata-Version: 2.1
Name: remoteunrar
Version: 0.9.2
Summary: Access rar file content hosted remotely without downloading the full file.
Home-page: https://github.com/muhammedfurkan/python-remoteunrar
Author: M.Furkan
Author-email: furkan@telegmail.com
License: MIT
Platform: UNKNOWN
Classifier: Intended Audience :: Developers
Classifier: Development Status :: 5 - Production/Stable
Classifier: License :: OSI Approved :: MIT License
Classifier: Programming Language :: Python
Classifier: Programming Language :: Python :: 2.7
Classifier: Programming Language :: Python :: 3
Classifier: Programming Language :: Python :: 3.3
Classifier: Programming Language :: Python :: 3.4
Classifier: Programming Language :: Python :: 3.5
Classifier: Programming Language :: Python :: 3.6
